{
  "project_info": {
    "project_number": "1029755035189",
    "project_id": "messangerdb-56f26",
    "storage_bucket": "messangerdb-56f26.appspot.com"
  },
  "client": [
    {
      "client_info": {
        "mobilesdk_app_id": "1:1029755035189:android:4d7b1d18ac1efe70955b7c",
        "android_client_info": {
          "package_name": "com.example.messanger"
        }
      },
      "oauth_client": [],
      "api_key": [
        {
          "current_key": "AIzaSyAh1pPgbFfwQzWnlBuAzmmVUxxBnyIUmrQ"
        }
      ],
      "services": {
        "appinvite_service": {
          "other_platform_oauth_client": []
        }
      }
    }
  ],
  "configuration_version": "1"
}